teradataexportcsv/__init__.py
teradataexportcsv/vernumber.py
teradataexportcsv-1.0.2.data/data/teradataexportcsv/LICENSE
teradataexportcsv-1.0.2.data/data/teradataexportcsv/README.md
teradataexportcsv-1.0.2.dist-info/METADATA
teradataexportcsv-1.0.2.dist-info/RECORD
teradataexportcsv-1.0.2.dist-info/WHEEL
teradataexportcsv-1.0.2.dist-info/top_level.txt
