Metadata-Version: 2.1
Name: teradataexportcsv
Version: 1.0.2
Summary: teradataexportcsv package
Home-page: http://www.teradata.com/
Author: Teradata Corporation
Author-email: teradatasql@teradata.com
License: Teradata License Agreement
Keywords: Teradata
Platform: Windows
Platform: MacOS X
Platform: Linux
Classifier: Development Status :: 5 - Production/Stable
Classifier: Programming Language :: Python :: 3 :: Only
Classifier: Programming Language :: Python :: 3.4
Classifier: Programming Language :: Python :: 3.5
Classifier: Programming Language :: Python :: 3.6
Classifier: Programming Language :: Python :: 3.7
Classifier: Programming Language :: Python :: 3.8
Classifier: Programming Language :: Python :: 3.9
Classifier: Programming Language :: Python :: 3.10
Classifier: Operating System :: Microsoft :: Windows
Classifier: Operating System :: MacOS :: MacOS X
Classifier: Operating System :: POSIX :: Linux
Classifier: Topic :: Database :: Front-Ends
Classifier: License :: Other/Proprietary License
Requires-Python: >=3.4
Requires-Dist: teradatasql
